graphql_ws/__init__.py
graphql_ws/aiohttp.py
graphql_ws/base.py
graphql_ws/base_async.py
graphql_ws/base_sync.py
graphql_ws/constants.py
graphql_ws/django_channels.py
graphql_ws/gevent.py
graphql_ws/observable_aiter.py
graphql_ws/websockets_lib.py
graphql_ws/django/__init__.py
graphql_ws/django/apps.py
graphql_ws/django/consumers.py
graphql_ws/django/routing.py
graphql_ws/django/subscriptions.py
graphql_ws/django/templates/graphene/graphiql.html
graphql_ws-0.4.3.dist-info/AUTHORS.rst
graphql_ws-0.4.3.dist-info/LICENSE
graphql_ws-0.4.3.dist-info/METADATA
graphql_ws-0.4.3.dist-info/WHEEL
graphql_ws-0.4.3.dist-info/top_level.txt
graphql_ws-0.4.3.dist-info/RECORD
